perseo_optimizer/__init__.py
perseo_optimizer/ansys_functions.py
perseo_optimizer/commands.py
perseo_optimizer/dataManagement.py
perseo_optimizer/graphicsManagement.py
perseo_optimizer/interface.py
perseo_optimizer/messages.py
perseo_optimizer/optimize.py
perseo_optimizer/pso.py
perseo_optimizer/simulate.py
perseo_optimizer-1.0.2.dist-info/LICENSE
perseo_optimizer-1.0.2.dist-info/METADATA
perseo_optimizer-1.0.2.dist-info/WHEEL
perseo_optimizer-1.0.2.dist-info/top_level.txt
perseo_optimizer-1.0.2.dist-info/RECORD
