Metadata-Version: 2.1
Name: perseo-optimizer
Version: 1.0.2
Summary: PerSeO: PSO Applied to RF Device Design
Home-page: https://github.com/ERA-2022/PerSeO
Author: German Chaparro, Jorge Cardenas, Oscar Restrepo, Sergio Mora, Jhon Vera and Jaime Angel
Author-email: gchaparrom@ecci.edu.co, jorge.cardenas3@udea.edu.co , orestrepog@ecci.edu.co, smoram@ecci.edu.co, jverav@ecci.edu.co, jaimea.angelm@ecci.edu.co
License: MIT
Classifier: Development Status :: 5 - Production/Stable
Classifier: Intended Audience :: Developers
Classifier: Topic :: Scientific/Engineering :: Physics
Classifier: Topic :: Software Development :: Libraries :: Python Modules
Classifier: Programming Language :: Python :: 3.10
Classifier: License :: OSI Approved :: MIT License
Classifier: Operating System :: OS Independent
Requires-Python: >=3.10
License-File: LICENSE
Requires-Dist: cycler ==0.11.0
Requires-Dist: fonttools ==4.31.2
Requires-Dist: joblib ==1.1.0
Requires-Dist: kiwisolver ==1.4.2
Requires-Dist: matplotlib ==3.5.1
Requires-Dist: numpy ==1.22.3
Requires-Dist: packaging ==21.3
Requires-Dist: pandas ==1.4.2
Requires-Dist: Pillow ==9.1.0
Requires-Dist: pyparsing ==3.0.7
Requires-Dist: python-dateutil ==2.8.2
Requires-Dist: pytz ==2022.1
Requires-Dist: scikit-learn ==1.1.1
Requires-Dist: scipy ==1.8.1
Requires-Dist: six ==1.16.0
Requires-Dist: threadpoolctl ==3.1.0
